ns_api.py
nsapi-3.2.1.dist-info/licenses/LICENSE
nsapi-3.2.1.dist-info/METADATA
nsapi-3.2.1.dist-info/WHEEL
nsapi-3.2.1.dist-info/top_level.txt
nsapi-3.2.1.dist-info/RECORD
