Metadata-Version: 2.4
Name: nsapi
Version: 3.2.1
Summary: NS api wrapper for Dutch Railways (Nationale Spoorwegen, NS), also called ns-api
Author-email: Michiel Scholten <michiel@diginaut.net>
License: MIT
Project-URL: Homepage, https://github.com/aquatix/ns-api/
Project-URL: Bug Tracker, https://github.com/aquatix/ns-api/issues
Keywords: api,automation,public transport
Classifier: Topic :: Software Development :: Libraries
Classifier: Development Status :: 5 - Production/Stable
Classifier: Intended Audience :: Developers
Classifier: License :: OSI Approved :: MIT License
Classifier: Programming Language :: Python :: 3
Requires-Python: >=3.10
License-File: LICENSE
Requires-Dist: pytz>2018.5
Dynamic: license-file
